django_pg_trunk/__init__.py
django_pg_trunk/admin.py
django_pg_trunk/apps.py
django_pg_trunk/models.py
django_pg_trunk/tests.py
django_pg_trunk/utils.py
django_pg_trunk/migrations/0001_create_pg_stat_statements_extension.py
django_pg_trunk/migrations/0002_create_query_statistic_model.py
django_pg_trunk/migrations/__init__.py
django_pg_trunk-0.1.3.dist-info/LICENSE
django_pg_trunk-0.1.3.dist-info/METADATA
django_pg_trunk-0.1.3.dist-info/WHEEL
django_pg_trunk-0.1.3.dist-info/top_level.txt
django_pg_trunk-0.1.3.dist-info/RECORD
