Metadata-Version: 2.1
Name: django-pg-trunk
Version: 0.1.3
Summary: A PostgreSQL profiler for Django that uses pg_stat_statements extension
Home-page: https://github.com/Hipo/django-pg-trunk
Author: Hipo
Author-email: faruk@hipo.biz
License: Apache-2.0
Platform: UNKNOWN
Classifier: Environment :: Web Environment
Classifier: Framework :: Django
Classifier: Intended Audience :: Developers
Classifier: License :: OSI Approved :: Apache Software License
Classifier: Operating System :: OS Independent
Classifier: Programming Language :: Python
Classifier: Programming Language :: Python :: 3.7
Classifier: Programming Language :: Python :: 3.8
Classifier: Programming Language :: Python :: 3.9
Classifier: Programming Language :: Python :: 3.10
Classifier: Topic :: Internet :: WWW/HTTP
Classifier: Topic :: Internet :: WWW/HTTP :: Dynamic Content
Requires-Python: >=3.7
License-File: LICENSE
Requires-Dist: Django (>=2.2)
Requires-Dist: psycopg2-binary (<2.9)
